sqlite_utils_sqlite_tg/__init__.py
sqlite_utils_sqlite_tg-0.0.1a19.dist-info/METADATA
sqlite_utils_sqlite_tg-0.0.1a19.dist-info/WHEEL
sqlite_utils_sqlite_tg-0.0.1a19.dist-info/entry_points.txt
sqlite_utils_sqlite_tg-0.0.1a19.dist-info/top_level.txt
sqlite_utils_sqlite_tg-0.0.1a19.dist-info/RECORD
