Metadata-Version: 2.1
Name: sqlite-utils-sqlite-tg
Version: 0.0.1a19
Home-page: https://TODO.com
Author: TODO
License: MIT License, Apache License, Version 2.0
Requires-Dist: sqlite-utils
Requires-Dist: sqlite-tg (==0.0.1-alpha.19)
